bhpy/__init__.py
bhpy/bh_connect.py
bhpy/bh_device_scan_wrapper.py
bhpy/bh_lv_wrapper.py
bhpy/spc_tdc_config.py
bhpy/spc_tdc_wrapper.py
bhpy/dll/ControlBDU.dll
bhpy/dll/ControlQC008.dll
bhpy/dll/bh_device_scan.dll
bhpy/dll/pms_800.dll
bhpy/dll/spc_qc_X04.dll
bhpy/dll/spc_qc_X08.dll
bhpy/examples/controll_bdu.py
bhpy/examples/spc_tdc_multicard_measurement.py
bhpy-3.3.0.dist-info/METADATA
bhpy-3.3.0.dist-info/WHEEL
bhpy-3.3.0.dist-info/licenses/LICENSE.txt
bhpy-3.3.0.dist-info/RECORD
