Metadata-Version: 2.4
Name: bhpy
Version: 3.3.0
Summary: Python bindings to use Becker & Hickls' hardware control dll and API
Project-URL: Homepage, https://www.becker-hickl.com/products/bhpy
Project-URL: Bug Tracker, https://github.com/bhmarscheck/bhpy/issues
Project-URL: Download, https://git.becker-hickl.com/products/bhpy/-/archive/v3.3.0/bhpy-v3.3.0.tar.gz
Author-email: Marscheck <marscheck@becker-hickl.de>
License-Expression: MIT
License-File: LICENSE.txt
Keywords: BH,Becker&Hickl,FLIM,Fluorescence lifetime,SPC,SPCM,TCSPC,molecular imaging,photon counting
Classifier: Development Status :: 5 - Production/Stable
Classifier: Intended Audience :: Developers
Classifier: Intended Audience :: Healthcare Industry
Classifier: Intended Audience :: Science/Research
Classifier: License :: OSI Approved :: MIT License
Classifier: Operating System :: OS Independent
Classifier: Programming Language :: Python :: 3
Classifier: Programming Language :: Python :: 3.10
Classifier: Programming Language :: Python :: 3.11
Classifier: Programming Language :: Python :: 3.12
Classifier: Topic :: Scientific/Engineering
Classifier: Topic :: Software Development :: Build Tools
Classifier: Topic :: Software Development :: Libraries
Classifier: Topic :: System :: Hardware :: Hardware Drivers
Requires-Python: >=3.10
Requires-Dist: appdirs<2,>=1.4.4
Requires-Dist: numpy<3,>=2.2.6
Requires-Dist: pycryptodome<4,>=3.23.0
Requires-Dist: zeroconf>=0.147.0
